{"data":{"site":{"siteMetadata":{"title":"La gaceta de la cabeza","author":"Joaquín Bravo Contreras"}},"markdownRemark":{"id":"a7bc6469-084f-5aec-a989-423f848190ff","excerpt":"","html":"<p><a href=\"http://flisol.cucea.udg.mx/\">FLISOL CUCEA 2017</a></p>\n<p>Durante la sesión aprenderemos a usar Drupal para desarrollar aplicaciones de manera rápida. Usaremos mucho la línea de comandos para ayudarnos a instalar drupal, generar módulos nuevos, lanzar un servidor de desarrollo y crear el código inicial de nuestra aplicación. Durante la sesión usaremos también git para llevar el control de versiones del código, y al finalizar tendremos el backend para una aplicación sencilla con todo y una interfaz administrativa completa para visualizar los datos en la aplicación.</p>","frontmatter":{"title":"Desarrollo rápido con Drupal","date":"May 03, 2017"}}},"pageContext":{"slug":"/desarrollo-rapido-con-drupal/","previous":{"fields":{"slug":"/suki/"},"frontmatter":{"title":"Suki"}},"next":null}}