{"data":{"site":{"siteMetadata":{"title":"La gaceta de la cabeza","author":"Joaquín Bravo Contreras"}},"markdownRemark":{"id":"42f256dc-73fb-5c5b-8a2e-1f20e352842b","excerpt":"","html":"","frontmatter":{"title":"","date":null,"tags":null}}},"pageContext":{"slug":"/crear-un-calendario-de-grupo-con-drupal/","previous":{"fields":{"slug":"/suki/"},"frontmatter":{"title":"Suki","aliases":[],"tags":[]}},"next":{"fields":{"slug":"/que-preferencia-sexual-quisieras-que-tuvieran-tus-hijos/"},"frontmatter":{"title":"","aliases":null,"tags":null}}}}